decision_making/__init__.py
decision_making/min_dependency.py
decision_making/ahp/__init__.py
decision_making/ahp/_ahp.py
decision_making/ahp/_helper_ahp.py
decision_making/copras/__init__.py
decision_making/copras/_copras.py
decision_making/copras/_helper_copras.py
decision_making/fuzzy_ahp/__init__.py
decision_making/fuzzy_ahp/_fuzzy_ahp.py
decision_making/fuzzy_ahp/_helper_fuzzy_ahp.py
decision_making/fuzzy_copras/__init__.py
decision_making/fuzzy_copras/_fuzzy_copras.py
decision_making/fuzzy_copras/_helper_fuzzy_copras.py
decision_making/fuzzy_topsis/__init__.py
decision_making/fuzzy_topsis/_fuzzy_topsis.py
decision_making/fuzzy_topsis/_helper_fuzzy_topsis.py
decision_making/topsis/__init__.py
decision_making/topsis/_helper_topsis.py
decision_making/topsis/_topsis.py
decision_making-1.0.dist-info/License.md
decision_making-1.0.dist-info/METADATA
decision_making-1.0.dist-info/WHEEL
decision_making-1.0.dist-info/top_level.txt
decision_making-1.0.dist-info/RECORD
