Metadata-Version: 2.1
Name: decision-making
Version: 1.0
Summary: A Python Package for Fuzzy Logic Technique in MCDM.
Maintainer: Eeshan Anand
Maintainer-email: e2002anand@gmail.com
License: MIT
Project-URL: Documentation, https://github.com/iamAnas-zzx/decision_making/tree/main/docx_words
Project-URL: Source Code, https://github.com/iamAnas-zzx/decision_making.git
Classifier: Intended Audience :: Science/Research
Classifier: Intended Audience :: Developers
Classifier: License :: OSI Approved :: MIT License
Classifier: Programming Language :: Python
Classifier: Topic :: Software Development
Classifier: Topic :: Scientific/Engineering
Classifier: Development Status :: 5 - Production/Stable
Classifier: Operating System :: OS Independent
Classifier: Programming Language :: Python :: 3.9
Classifier: Programming Language :: Python :: Implementation :: CPython
Classifier: Programming Language :: Python :: Implementation :: PyPy
Requires-Python: >=3.9
License-File: License.md
Requires-Dist: numpy >=1.26.4
Requires-Dist: scipy >=1.13.0
Requires-Dist: pandas >=2.2.2
